image_processing/__init__.py
image_processing/processing/__init__.py
image_processing/processing/combination.py
image_processing/processing/transformation.py
image_processing/utils/__init__.py
image_processing/utils/io.py
image_processing/utils/plot.py
my image_processing/__init__.py
my image_processing/processing/__init__.py
my image_processing/processing/combination.py
my image_processing/processing/transformation.py
my image_processing/utils/__init__.py
my image_processing/utils/io.py
my image_processing/utils/plot.py
my image_processing_Rhuan/__init__.py
my image_processing_Rhuan/processing/__init__.py
my image_processing_Rhuan/processing/combination.py
my image_processing_Rhuan/processing/transformation.py
my image_processing_Rhuan/utils/__init__.py
my image_processing_Rhuan/utils/io.py
my image_processing_Rhuan/utils/plot.py
my_image_processing_rhuan-0.0.2.dist-info/METADATA
my_image_processing_rhuan-0.0.2.dist-info/WHEEL
my_image_processing_rhuan-0.0.2.dist-info/top_level.txt
my_image_processing_rhuan-0.0.2.dist-info/RECORD
