Metadata-Version: 2.1
Name: my_image_processing_rhuan
Version: 0.0.2
Summary: Image Processing Packate
Home-page: https://github.com/rhuanvictor/image-processing-package
Author: Rhuan
Requires-Python: >=3.8
